nangram/__init__.py
nangram/element.py
nangram/grammar.py
nangram/node.py
nangram/util.py
nangram-0.0.6.dist-info/LICENSE
nangram-0.0.6.dist-info/METADATA
nangram-0.0.6.dist-info/WHEEL
nangram-0.0.6.dist-info/top_level.txt
nangram-0.0.6.dist-info/RECORD
